{"sections":[{"name":"Couplet","measures":[1],"lyrics":["Esta mañana, me he levantado","Oh bella ciao, bella ciao, bella ciao, ciao, ciao","Esta mañana, me he levantado","Y he descubierto al invasor"]},{"name":"Couplet","measures":[1],"lyrics":["Oh compañero, quiero ir contigo","Oh bella ciao, bella ciao, bella ciao, ciao, ciao","Oh compañero, quiero ir contigo","Porque me siento aqui morir"]},{"name":"Couplet","measures":[1],"lyrics":["Y si yo caigo en la batalla","Oh bella ciao, bella ciao, bella ciao, ciao, ciao","Y si yo caigo en la batalla","Coge en tus manos mi fusil"]},{"name":"Couplet","measures":[1],"lyrics":["Cava una fosa en la montaña","Oh bella ciao, bella ciao, bella ciao, ciao, ciao","Cava una fosa en la montaña","Bajo la sombra de una flor","Cava una fosa en la montaña","Se dira que bella flor"]}]}